chess_tcn/__init__.py
chess_tcn-0.0.1.dist-info/licenses/LICENSE
chess_tcn-0.0.1.dist-info/METADATA
chess_tcn-0.0.1.dist-info/WHEEL
chess_tcn-0.0.1.dist-info/top_level.txt
chess_tcn-0.0.1.dist-info/RECORD
