Metadata-Version: 2.4
Name: chess-tcn
Version: 0.0.1
Summary: Encode and decode TCN, a move format used by Chess.com's API
Author: chess-tcn
License: MIT
Classifier: Programming Language :: Python :: 3
Classifier: License :: OSI Approved :: MIT License
Classifier: Operating System :: OS Independent
License-File: LICENSE
Dynamic: license-file
